QuantileFlow/__init__.py
QuantileFlow/ddsketch/__init__.py
QuantileFlow/ddsketch/core.py
QuantileFlow/ddsketch/mapping/__init__.py
QuantileFlow/ddsketch/mapping/base.py
QuantileFlow/ddsketch/mapping/cubic_interpolation.py
QuantileFlow/ddsketch/mapping/linear_interpolation.py
QuantileFlow/ddsketch/mapping/logarithmic.py
QuantileFlow/ddsketch/storage/__init__.py
QuantileFlow/ddsketch/storage/base.py
QuantileFlow/ddsketch/storage/contiguous.py
QuantileFlow/ddsketch/storage/sparse.py
QuantileFlow/hdrhistogram/__init__.py
QuantileFlow/hdrhistogram/core.py
QuantileFlow/momentsketch/__init__.py
QuantileFlow/momentsketch/core.py
QuantileFlow/momentsketch/example.py
QuantileFlow/momentsketch/optimizer.py
QuantileFlow/momentsketch/simple_moment_sketch.py
QuantileFlow/momentsketch/utils.py
docs/__init__.py
docs/conf.py
quantileflow-1.0.0.dist-info/licenses/LICENSE
quantileflow-1.0.0.dist-info/licenses/LICENSE.txt
tests/__init__.py
tests/hdrhistogram/__init__.py
tests/hdrhistogram/test_hdr.py
tests/momentsketch/__init__.py
tests/momentsketch/core_test.py
tests/momentsketch/integration_test.py
tests/momentsketch/optimizer_test.py
tests/momentsketch/simple_ms_test.py
tests/momentsketch/utils_test.py
quantileflow-1.0.0.dist-info/METADATA
quantileflow-1.0.0.dist-info/WHEEL
quantileflow-1.0.0.dist-info/top_level.txt
quantileflow-1.0.0.dist-info/RECORD
