Metadata-Version: 2.4
Name: QuantileFlow
Version: 1.0.0
Summary: This package provides API and functionality to efficiently compute quantiles for anomaly detection in service/system logs. Developed under LogFlow-AI initiative.
Home-page: https://github.com/LogFlow-AI/QuantileFlow
Author: Dhyey Mavani
License: Apache
Keywords: QuantileFlow
Classifier: Programming Language :: Python
License-File: LICENSE
License-File: LICENSE.txt
Requires-Dist: numpy
Requires-Dist: pandas
Requires-Dist: pytest
Requires-Dist: coverage
Requires-Dist: scipy
Requires-Dist: matplotlib
Dynamic: author
Dynamic: classifier
Dynamic: description
Dynamic: description-content-type
Dynamic: home-page
Dynamic: keywords
Dynamic: license
Dynamic: license-file
Dynamic: requires-dist
Dynamic: summary
